{"code": "GER", "description": "German", "entries": 26, "data": [{"id": 448145, "term": "200720", "termDesc": "Spring 2007", "courseReferenceNumber": "18038", "partOfTerm": "1", "courseNumber": "002R", "subject": "GER", "subjectDescription": "German", "sequenceNumber": "001", "campusDescription": "Riverside", "scheduleTypeDescription": "Lecture", "courseTitle": "READING KNOWLEDGE", "creditHours": 4, "maximumEnrollment": 20, "enrollment": 13, "seatsAvailable": 7, "waitCapacity": 999, "waitCount": 0, "waitAvailable": 999, "crossList": null, "crossListCapacity": null, "crossListCount": null, "crossListAvailable": null, "creditHourHigh": null, "creditHourLow": 4, "creditHourIndicator": null, "openSection": true, "linkIdentifier": null, "isSectionLinked": false, "subjectCourse": "GER002R", "faculty": [{"bannerId": "317582", "category": null, "class": "net.hedtech.banner.student.faculty.FacultyResultDecorator", "courseReferenceNumber": "18038", "displayName": "Thuerwaechter, Sabine", "emailAddress": "sabine.thuerwaechter@email.ucr.edu", "primaryIndicator": true, "term": "200720"}], "meetingsFaculty": [{"category": "01", "class": "net.hedtech.banner.student.schedule.SectionSessionDecorator", "courseReferenceNumber": "18038", "faculty": [], "meetingTime": {"beginTime": "1710", "building": "ENGR2", "buildingDescription": "Engineering Building #2", "campus": "C", "campusDescription": "Riverside", "category": "01", "class": "net.hedtech.banner.general.overall.MeetingTimeDecorator", "courseReferenceNumber": "18038", "creditHourSession": 4.0, "endDate": "06/08/2007", "endTime": "1900", "friday": false, "hoursWeek": 4.0, "meetingScheduleType": "LEC", "meetingType": "LEC", "meetingTypeDescription": "Lecture", "monday": true, "room": "141", "saturday": false, "startDate": "04/02/2007", "sunday": false, "term": "200720", "thursday": false, "tuesday": false, "wednesday": true}, "term": "200720"}], "reservedSeatSummary": null, "sectionAttributes": null, "instructionalMethod": "I", "instructionalMethodDescription": "In-Person"}, {"id": 448146, "term": "200720", "termDesc": "Spring 2007", "courseReferenceNumber": "14423", "partOfTerm": "1", "courseNumber": "003", "subject": "GER", "subjectDescription": "German", "sequenceNumber": "001", "campusDescription": "Riverside", "scheduleTypeDescription": "Lecture", "courseTitle": "ELEMENTARY GERMAN", "creditHours": 4, "maximumEnrollment": 25, "enrollment": 21, "seatsAvailable": 4, "waitCapacity": 5, "waitCount": 0, "waitAvailable": 5, "crossList": null, "crossListCapacity": null, "crossListCount": null, "crossListAvailable": null, "creditHourHigh": null, "creditHourLow": 4, "creditHourIndicator": null, "openSection": true, "linkIdentifier": null, "isSectionLinked": false, "subjectCourse": "GER003", "faculty": [{"bannerId": "317582", "category": null, "class": "net.hedtech.banner.student.faculty.FacultyResultDecorator", "courseReferenceNumber": "14423", "displayName": "Thuerwaechter, Sabine", "emailAddress": "sabine.thuerwaechter@email.ucr.edu", "primaryIndicator": true, "term": "200720"}, {"bannerId": "352385", "category": null, "class": "net.hedtech.banner.student.faculty.FacultyResultDecorator", "courseReferenceNumber": "14423", "displayName": "Savoth, Eric", "emailAddress": "eric.savoth@email.ucr.edu", "primaryIndicator": false, "term": "200720"}], "meetingsFaculty": [{"category": "01", "class": "net.hedtech.banner.student.schedule.SectionSessionDecorator", "courseReferenceNumber": "14423", "faculty": [], "meetingTime": {"beginTime": "0910", "building": "HMNSS", "buildingDescription": "Humanities and Social Sciences", "campus": "C", "campusDescription": "Riverside", "category": "01", "class": "net.hedtech.banner.general.overall.MeetingTimeDecorator", "courseReferenceNumber": "14423", "creditHourSession": 4.0, "endDate": "06/08/2007", "endTime": "1000", "friday": false, "hoursWeek": 4.0, "meetingScheduleType": "LEC", "meetingType": "LEC", "meetingTypeDescription": "Lecture", "monday": true, "room": "1401", "saturday": false, "startDate": "04/02/2007", "sunday": false, "term": "200720", "thursday": true, "tuesday": true, "wednesday": true}, "term": "200720"}], "reservedSeatSummary": null, "sectionAttributes": null, "instructionalMethod": "I", "instructionalMethodDescription": "In-Person"}, {"id": 448147, "term": "200720", "termDesc": "Spring 2007", "courseReferenceNumber": "14424", "partOfTerm": "1", "courseNumber": "003", "subject": "GER", "subjectDescription": "German", "sequenceNumber": "002", "campusDescription": "Riverside", "scheduleTypeDescription": "Lecture", "courseTitle": "ELEMENTARY GERMAN", "creditHours": 4, "maximumEnrollment": 25, "enrollment": 24, "seatsAvailable": 1, "waitCapacity": 5, "waitCount": 0, "waitAvailable": 5, "crossList": null, "crossListCapacity": null, "crossListCount": null, "crossListAvailable": null, "creditHourHigh": null, "creditHourLow": 4, "creditHourIndicator": null, "openSection": true, "linkIdentifier": null, "isSectionLinked": false, "subjectCourse": "GER003", "faculty": [{"bannerId": "317582", "category": null, "class": "net.hedtech.banner.student.faculty.FacultyResultDecorator", "courseReferenceNumber": "14424", "displayName": "Thuerwaechter, Sabine", "emailAddress": "sabine.thuerwaechter@email.ucr.edu", "primaryIndicator": true, "term": "200720"}], "meetingsFaculty": [{"category": "01", "class": "net.hedtech.banner.student.schedule.SectionSessionDecorator", "courseReferenceNumber": "14424", "faculty": [], "meetingTime": {"beginTime": "1010", "building": "HMNSS", "buildingDescription": "Humanities and Social Sciences", "campus": "C", "campusDescription": "Riverside", "category": "01", "class": "net.hedtech.banner.general.overall.MeetingTimeDecorator", "courseReferenceNumber": "14424", "creditHourSession": 4.0, "endDate": "06/08/2007", "endTime": "1100", "friday": false, "hoursWeek": 4.0, "meetingScheduleType": "LEC", "meetingType": "LEC", "meetingTypeDescription": "Lecture", "monday": true, "room": "1401", "saturday": false, "startDate": "04/02/2007", "sunday": false, "term": "200720", "thursday": true, "tuesday": true, "wednesday": true}, "term": "200720"}], "reservedSeatSummary": null, "sectionAttributes": null, "instructionalMethod": "I", "instructionalMethodDescription": "In-Person"}, {"id": 448148, "term": "200720", "termDesc": "Spring 2007", "courseReferenceNumber": "14425", "partOfTerm": "1", "courseNumber": "090", "subject": "GER", "subjectDescription": "German", "sequenceNumber": "001", "campusDescription": "Riverside", "scheduleTypeDescription": "Tutorial", "courseTitle": "SPECIAL STUDIES", "creditHours": null, "maximumEnrollment": 999, "enrollment": 0, "seatsAvailable": 999, "waitCapacity": 0, "waitCount": 0, "waitAvailable": 0, "crossList": null, "crossListCapacity": null, "crossListCount": null, "crossListAvailable": null, "creditHourHigh": 3, "creditHourLow": 1, "creditHourIndicator": "TO", "openSection": true, "linkIdentifier": null, "isSectionLinked": false, "subjectCourse": "GER090", "faculty": [{"bannerId": "314395", "category": null, "class": "net.hedtech.banner.student.faculty.FacultyResultDecorator", "courseReferenceNumber": "14425", "displayName": "The Staff, .", "emailAddress": null, "primaryIndicator": true, "term": "200720"}], "meetingsFaculty": [{"category": "01", "class": "net.hedtech.banner.student.schedule.SectionSessionDecorator", "courseReferenceNumber": "14425", "faculty": [], "meetingTime": {"beginTime": null, "building": "TBA", "buildingDescription": "To Be Announced", "campus": "C", "campusDescription": "Riverside", "category": "01", "class": "net.hedtech.banner.general.overall.MeetingTimeDecorator", "courseReferenceNumber": "14425", "creditHourSession": 1.0, "endDate": "06/08/2007", "endTime": null, "friday": false, "hoursWeek": 0.0, "meetingScheduleType": "TUT", "meetingType": "TUT", "meetingTypeDescription": "Tutorial", "monday": false, "room": null, "saturday": false, "startDate": "04/02/2007", "sunday": false, "term": "200720", "thursday": false, "tuesday": false, "wednesday": false}, "term": "200720"}], "reservedSeatSummary": null, "sectionAttributes": null, "instructionalMethod": "I", "instructionalMethodDescription": "In-Person"}, {"id": 448149, "term": "200720", "termDesc": "Spring 2007", "courseReferenceNumber": "14426", "partOfTerm": "1", "courseNumber": "103B", "subject": "GER", "subjectDescription": "German", "sequenceNumber": "001", "campusDescription": "Riverside", "scheduleTypeDescription": "Lecture", "courseTitle": "ADVNCD COMP &amp; CNVRSATION", "creditHours": 4, "maximumEnrollment": 25, "enrollment": 10, "seatsAvailable": 15, "waitCapacity": 0, "waitCount": 0, "waitAvailable": 0, "crossList": null, "crossListCapacity": null, "crossListCount": null, "crossListAvailable": null, "creditHourHigh": null, "creditHourLow": 4, "creditHourIndicator": null, "openSection": true, "linkIdentifier": null, "isSectionLinked": false, "subjectCourse": "GER103B", "faculty": [{"bannerId": "317582", "category": null, "class": "net.hedtech.banner.student.faculty.FacultyResultDecorator", "courseReferenceNumber": "14426", "displayName": "Thuerwaechter, Sabine", "emailAddress": "sabine.thuerwaechter@email.ucr.edu", "primaryIndicator": true, "term": "200720"}], "meetingsFaculty": [{"category": "01", "class": "net.hedtech.banner.student.schedule.SectionSessionDecorator", "courseReferenceNumber": "14426", "faculty": [], "meetingTime": {"beginTime": "1240", "building": "WAT", "buildingDescription": "Gordon Watkins Hall", "campus": "C", "campusDescription": "Riverside", "category": "01", "class": "net.hedtech.banner.general.overall.MeetingTimeDecorator", "courseReferenceNumber": "14426", "creditHourSession": 4.0, "endDate": "06/08/2007", "endTime": "1400", "friday": false, "hoursWeek": 4.0, "meetingScheduleType": "LEC", "meetingType": "LEC", "meetingTypeDescription": "Lecture", "monday": false, "room": "2141", "saturday": false, "startDate": "04/02/2007", "sunday": false, "term": "200720", "thursday": true, "tuesday": true, "wednesday": false}, "term": "200720"}], "reservedSeatSummary": null, "sectionAttributes": null, "instructionalMethod": "I", "instructionalMethodDescription": "In-Person"}, {"id": 448151, "term": "200720", "termDesc": "Spring 2007", "courseReferenceNumber": "14430", "partOfTerm": "1", "courseNumber": "190", "subject": "GER", "subjectDescription": "German", "sequenceNumber": "110", "campusDescription": "Riverside", "scheduleTypeDescription": "Tutorial", "courseTitle": "SPECIAL STUDIES", "creditHours": null, "maximumEnrollment": 30, "enrollment": 0, "seatsAvailable": 30, "waitCapacity": 0, "waitCount": 0, "waitAvailable": 0, "crossList": null, "crossListCapacity": null, "crossListCount": null, "crossListAvailable": null, "creditHourHigh": 5, "creditHourLow": 1, "creditHourIndicator": "TO", "openSection": true, "linkIdentifier": null, "isSectionLinked": false, "subjectCourse": "GER190", "faculty": [{"bannerId": "338983", "category": null, "class": "net.hedtech.banner.student.faculty.FacultyResultDecorator", "courseReferenceNumber": "14430", "displayName": "Ochs, Sylvia", "emailAddress": null, "primaryIndicator": true, "term": "200720"}], "meetingsFaculty": [{"category": "01", "class": "net.hedtech.banner.student.schedule.SectionSessionDecorator", "courseReferenceNumber": "14430", "faculty": [], "meetingTime": {"beginTime": null, "building": "TBA", "buildingDescription": "To Be Announced", "campus": "C", "campusDescription": "Riverside", "category": "01", "class": "net.hedtech.banner.general.overall.MeetingTimeDecorator", "courseReferenceNumber": "14430", "creditHourSession": 1.0, "endDate": "06/08/2007", "endTime": null, "friday": false, "hoursWeek": 0.0, "meetingScheduleType": "TUT", "meetingType": "TUT", "meetingTypeDescription": "Tutorial", "monday": false, "room": null, "saturday": false, "startDate": "04/02/2007", "sunday": false, "term": "200720", "thursday": false, "tuesday": false, "wednesday": false}, "term": "200720"}], "reservedSeatSummary": null, "sectionAttributes": null, "instructionalMethod": "I", "instructionalMethodDescription": "In-Person"}, {"id": 448150, "term": "200720", "termDesc": "Spring 2007", "courseReferenceNumber": "14429", "partOfTerm": "1", "courseNumber": "190", "subject": "GER", "subjectDescription": "German", "sequenceNumber": "11O", "campusDescription": "Riverside", "scheduleTypeDescription": "Tutorial", "courseTitle": "SPECIAL STUDIES", "creditHours": null, "maximumEnrollment": 30, "enrollment": 0, "seatsAvailable": 30, "waitCapacity": 0, "waitCount": 0, "waitAvailable": 0, "crossList": null, "crossListCapacity": null, "crossListCount": null, "crossListAvailable": null, "creditHourHigh": 5, "creditHourLow": 1, "creditHourIndicator": "TO", "openSection": true, "linkIdentifier": null, "isSectionLinked": false, "subjectCourse": "GER190", "faculty": [{"bannerId": "338983", "category": null, "class": "net.hedtech.banner.student.faculty.FacultyResultDecorator", "courseReferenceNumber": "14429", "displayName": "Ochs, Sylvia", "emailAddress": null, "primaryIndicator": true, "term": "200720"}], "meetingsFaculty": [{"category": "01", "class": "net.hedtech.banner.student.schedule.SectionSessionDecorator", "courseReferenceNumber": "14429", "faculty": [], "meetingTime": {"beginTime": null, "building": "TBA", "buildingDescription": "To Be Announced", "campus": "C", "campusDescription": "Riverside", "category": "01", "class": "net.hedtech.banner.general.overall.MeetingTimeDecorator", "courseReferenceNumber": "14429", "creditHourSession": 1.0, "endDate": "06/08/2007", "endTime": null, "friday": false, "hoursWeek": 0.0, "meetingScheduleType": "TUT", "meetingType": "TUT", "meetingTypeDescription": "Tutorial", "monday": false, "room": null, "saturday": false, "startDate": "04/02/2007", "sunday": false, "term": "200720", "thursday": false, "tuesday": false, "wednesday": false}, "term": "200720"}], "reservedSeatSummary": null, "sectionAttributes": null, "instructionalMethod": "I", "instructionalMethodDescription": "In-Person"}, {"id": 448152, "term": "200720", "termDesc": "Spring 2007", "courseReferenceNumber": "14431", "partOfTerm": "1", "courseNumber": "190", "subject": "GER", "subjectDescription": "German", "sequenceNumber": "25H", "campusDescription": "Riverside", "scheduleTypeDescription": "Tutorial", "courseTitle": "SPECIAL STUDIES", "creditHours": null, "maximumEnrollment": 30, "enrollment": 0, "seatsAvailable": 30, "waitCapacity": 0, "waitCount": 0, "waitAvailable": 0, "crossList": null, "crossListCapacity": null, "crossListCount": null, "crossListAvailable": null, "creditHourHigh": 5, "creditHourLow": 1, "creditHourIndicator": "TO", "openSection": true, "linkIdentifier": null, "isSectionLinked": false, "subjectCourse": "GER190", "faculty": [{"bannerId": "335455", "category": null, "class": "net.hedtech.banner.student.faculty.FacultyResultDecorator", "courseReferenceNumber": "14431", "displayName": "Hammer, Stephanie", "emailAddress": "stephanie.hammer@ucr.edu", "primaryIndicator": true, "term": "200720"}], "meetingsFaculty": [{"category": "01", "class": "net.hedtech.banner.student.schedule.SectionSessionDecorator", "courseReferenceNumber": "14431", "faculty": [], "meetingTime": {"beginTime": null, "building": "TBA", "buildingDescription": "To Be Announced", "campus": "C", "campusDescription": "Riverside", "category": "01", "class": "net.hedtech.banner.general.overall.MeetingTimeDecorator", "courseReferenceNumber": "14431", "creditHourSession": 1.0, "endDate": "06/08/2007", "endTime": null, "friday": false, "hoursWeek": 0.0, "meetingScheduleType": "TUT", "meetingType": "TUT", "meetingTypeDescription": "Tutorial", "monday": false, "room": null, "saturday": false, "startDate": "04/02/2007", "sunday": false, "term": "200720", "thursday": false, "tuesday": false, "wednesday": false}, "term": "200720"}], "reservedSeatSummary": null, "sectionAttributes": null, "instructionalMethod": "I", "instructionalMethodDescription": "In-Person"}, {"id": 448153, "term": "200720", "termDesc": "Spring 2007", "courseReferenceNumber": "14432", "partOfTerm": "1", "courseNumber": "190", "subject": "GER", "subjectDescription": "German", "sequenceNumber": "34G", "campusDescription": "Riverside", "scheduleTypeDescription": "Tutorial", "courseTitle": "SPECIAL STUDIES", "creditHours": null, "maximumEnrollment": 30, "enrollment": 0, "seatsAvailable": 30, "waitCapacity": 0, "waitCount": 0, "waitAvailable": 0, "crossList": null, "crossListCapacity": null, "crossListCount": null, "crossListAvailable": null, "creditHourHigh": 5, "creditHourLow": 1, "creditHourIndicator": "TO", "openSection": true, "linkIdentifier": null, "isSectionLinked": false, "subjectCourse": "GER190", "faculty": [{"bannerId": "338025", "category": null, "class": "net.hedtech.banner.student.faculty.FacultyResultDecorator", "courseReferenceNumber": "14432", "displayName": "Grimm, Reinhold", "emailAddress": null, "primaryIndicator": true, "term": "200720"}], "meetingsFaculty": [{"category": "01", "class": "net.hedtech.banner.student.schedule.SectionSessionDecorator", "courseReferenceNumber": "14432", "faculty": [], "meetingTime": {"beginTime": null, "building": "TBA", "buildingDescription": "To Be Announced", "campus": "C", "campusDescription": "Riverside", "category": "01", "class": "net.hedtech.banner.general.overall.MeetingTimeDecorator", "courseReferenceNumber": "14432", "creditHourSession": 1.0, "endDate": "06/08/2007", "endTime": null, "friday": false, "hoursWeek": 0.0, "meetingScheduleType": "TUT", "meetingType": "TUT", "meetingTypeDescription": "Tutorial", "monday": false, "room": null, "saturday": false, "startDate": "04/02/2007", "sunday": false, "term": "200720", "thursday": false, "tuesday": false, "wednesday": false}, "term": "200720"}], "reservedSeatSummary": null, "sectionAttributes": null, "instructionalMethod": "I", "instructionalMethodDescription": "In-Person"}, {"id": 448154, "term": "200720", "termDesc": "Spring 2007", "courseReferenceNumber": "19356", "partOfTerm": "1", "courseNumber": "190", "subject": "GER", "subjectDescription": "German", "sequenceNumber": "55D", "campusDescription": "Riverside", "scheduleTypeDescription": "Tutorial", "courseTitle": "SPECIAL STUDIES", "creditHours": null, "maximumEnrollment": 30, "enrollment": 2, "seatsAvailable": 28, "waitCapacity": 999, "waitCount": 0, "waitAvailable": 999, "crossList": null, "crossListCapacity": null, "crossListCount": null, "crossListAvailable": null, "creditHourHigh": 5, "creditHourLow": 1, "creditHourIndicator": "TO", "openSection": true, "linkIdentifier": null, "isSectionLinked": false, "subjectCourse": "GER190", "faculty": [{"bannerId": "328275", "category": null, "class": "net.hedtech.banner.student.faculty.FacultyResultDecorator", "courseReferenceNumber": "19356", "displayName": "Doran, Sabine", "emailAddress": null, "primaryIndicator": true, "term": "200720"}], "meetingsFaculty": [{"category": "01", "class": "net.hedtech.banner.student.schedule.SectionSessionDecorator", "courseReferenceNumber": "19356", "faculty": [], "meetingTime": {"beginTime": null, "building": "TBA", "buildingDescription": "To Be Announced", "campus": "C", "campusDescription": "Riverside", "category": "01", "class": "net.hedtech.banner.general.overall.MeetingTimeDecorator", "courseReferenceNumber": "19356", "creditHourSession": 1.0, "endDate": "06/08/2007", "endTime": null, "friday": false, "hoursWeek": 0.0, "meetingScheduleType": "TUT", "meetingType": "TUT", "meetingTypeDescription": "Tutorial", "monday": false, "room": null, "saturday": false, "startDate": "04/02/2007", "sunday": false, "term": "200720", "thursday": false, "tuesday": false, "wednesday": false}, "term": "200720"}], "reservedSeatSummary": null, "sectionAttributes": null, "instructionalMethod": "I", "instructionalMethodDescription": "In-Person"}, {"id": 448155, "term": "200720", "termDesc": "Spring 2007", "courseReferenceNumber": "14433", "partOfTerm": "1", "courseNumber": "290", "subject": "GER", "subjectDescription": "German", "sequenceNumber": "001", "campusDescription": "Riverside", "scheduleTypeDescription": "Research", "courseTitle": "DIRECTED STUDIES", "creditHours": null, "maximumEnrollment": 999, "enrollment": 0, "seatsAvailable": 999, "waitCapacity": 0, "waitCount": 0, "waitAvailable": 0, "crossList": null, "crossListCapacity": null, "crossListCount": null, "crossListAvailable": null, "creditHourHigh": 6, "creditHourLow": 1, "creditHourIndicator": "TO", "openSection": true, "linkIdentifier": null, "isSectionLinked": false, "subjectCourse": "GER290", "faculty": [{"bannerId": "314395", "category": null, "class": "net.hedtech.banner.student.faculty.FacultyResultDecorator", "courseReferenceNumber": "14433", "displayName": "The Staff, .", "emailAddress": null, "primaryIndicator": true, "term": "200720"}], "meetingsFaculty": [{"category": "01", "class": "net.hedtech.banner.student.schedule.SectionSessionDecorator", "courseReferenceNumber": "14433", "faculty": [], "meetingTime": {"beginTime": null, "building": "TBA", "buildingDescription": "To Be Announced", "campus": "C", "campusDescription": "Riverside", "category": "01", "class": "net.hedtech.banner.general.overall.MeetingTimeDecorator", "courseReferenceNumber": "14433", "creditHourSession": 1.0, "endDate": "06/08/2007", "endTime": null, "friday": false, "hoursWeek": 0.0, "meetingScheduleType": "RES", "meetingType": "RES", "meetingTypeDescription": "Research", "monday": false, "room": null, "saturday": false, "startDate": "04/02/2007", "sunday": false, "term": "200720", "thursday": false, "tuesday": false, "wednesday": false}, "term": "200720"}], "reservedSeatSummary": null, "sectionAttributes": null, "instructionalMethod": "I", "instructionalMethodDescription": "In-Person"}, {"id": 448156, "term": "200720", "termDesc": "Spring 2007", "courseReferenceNumber": "14434", "partOfTerm": "1", "courseNumber": "290", "subject": "GER", "subjectDescription": "German", "sequenceNumber": "02D", "campusDescription": "Riverside", "scheduleTypeDescription": "Research", "courseTitle": "DIRECTED STUDIES", "creditHours": null, "maximumEnrollment": 30, "enrollment": 0, "seatsAvailable": 30, "waitCapacity": 0, "waitCount": 0, "waitAvailable": 0, "crossList": null, "crossListCapacity": null, "crossListCount": null, "crossListAvailable": null, "creditHourHigh": 6, "creditHourLow": 1, "creditHourIndicator": "TO", "openSection": true, "linkIdentifier": null, "isSectionLinked": false, "subjectCourse": "GER290", "faculty": [{"bannerId": "351868", "category": null, "class": "net.hedtech.banner.student.faculty.FacultyResultDecorator", "courseReferenceNumber": "14434", "displayName": "Daviau, Donald", "emailAddress": null, "primaryIndicator": true, "term": "200720"}], "meetingsFaculty": [{"category": "01", "class": "net.hedtech.banner.student.schedule.SectionSessionDecorator", "courseReferenceNumber": "14434", "faculty": [], "meetingTime": {"beginTime": null, "building": "TBA", "buildingDescription": "To Be Announced", "campus": "C", "campusDescription": "Riverside", "category": "01", "class": "net.hedtech.banner.general.overall.MeetingTimeDecorator", "courseReferenceNumber": "14434", "creditHourSession": 1.0, "endDate": "06/08/2007", "endTime": null, "friday": false, "hoursWeek": 0.0, "meetingScheduleType": "RES", "meetingType": "RES", "meetingTypeDescription": "Research", "monday": false, "room": null, "saturday": false, "startDate": "04/02/2007", "sunday": false, "term": "200720", "thursday": false, "tuesday": false, "wednesday": false}, "term": "200720"}], "reservedSeatSummary": null, "sectionAttributes": null, "instructionalMethod": "I", "instructionalMethodDescription": "In-Person"}, {"id": 448157, "term": "200720", "termDesc": "Spring 2007", "courseReferenceNumber": "14435", "partOfTerm": "1", "courseNumber": "290", "subject": "GER", "subjectDescription": "German", "sequenceNumber": "11G", "campusDescription": "Riverside", "scheduleTypeDescription": "Research", "courseTitle": "DIRECTED STUDIES", "creditHours": null, "maximumEnrollment": 30, "enrollment": 0, "seatsAvailable": 30, "waitCapacity": 0, "waitCount": 0, "waitAvailable": 0, "crossList": null, "crossListCapacity": null, "crossListCount": null, "crossListAvailable": null, "creditHourHigh": 6, "creditHourLow": 1, "creditHourIndicator": "TO", "openSection": true, "linkIdentifier": null, "isSectionLinked": false, "subjectCourse": "GER290", "faculty": [{"bannerId": "335458", "category": null, "class": "net.hedtech.banner.student.faculty.FacultyResultDecorator", "courseReferenceNumber": "14435", "displayName": "Gugelberger, Georg", "emailAddress": "georg.gugelberger@ucr.edu", "primaryIndicator": true, "term": "200720"}], "meetingsFaculty": [{"category": "01", "class": "net.hedtech.banner.student.schedule.SectionSessionDecorator", "courseReferenceNumber": "14435", "faculty": [], "meetingTime": {"beginTime": null, "building": "TBA", "buildingDescription": "To Be Announced", "campus": "C", "campusDescription": "Riverside", "category": "01", "class": "net.hedtech.banner.general.overall.MeetingTimeDecorator", "courseReferenceNumber": "14435", "creditHourSession": 1.0, "endDate": "06/08/2007", "endTime": null, "friday": false, "hoursWeek": 0.0, "meetingScheduleType": "RES", "meetingType": "RES", "meetingTypeDescription": "Research", "monday": false, "room": null, "saturday": false, "startDate": "04/02/2007", "sunday": false, "term": "200720", "thursday": false, "tuesday": false, "wednesday": false}, "term": "200720"}], "reservedSeatSummary": null, "sectionAttributes": null, "instructionalMethod": "I", "instructionalMethodDescription": "In-Person"}, {"id": 448158, "term": "200720", "termDesc": "Spring 2007", "courseReferenceNumber": "14436", "partOfTerm": "1", "courseNumber": "290", "subject": "GER", "subjectDescription": "German", "sequenceNumber": "25H", "campusDescription": "Riverside", "scheduleTypeDescription": "Research", "courseTitle": "DIRECTED STUDIES", "creditHours": null, "maximumEnrollment": 30, "enrollment": 0, "seatsAvailable": 30, "waitCapacity": 0, "waitCount": 0, "waitAvailable": 0, "crossList": null, "crossListCapacity": null, "crossListCount": null, "crossListAvailable": null, "creditHourHigh": 6, "creditHourLow": 1, "creditHourIndicator": "TO", "openSection": true, "linkIdentifier": null, "isSectionLinked": false, "subjectCourse": "GER290", "faculty": [{"bannerId": "335455", "category": null, "class": "net.hedtech.banner.student.faculty.FacultyResultDecorator", "courseReferenceNumber": "14436", "displayName": "Hammer, Stephanie", "emailAddress": "stephanie.hammer@ucr.edu", "primaryIndicator": true, "term": "200720"}], "meetingsFaculty": [{"category": "01", "class": "net.hedtech.banner.student.schedule.SectionSessionDecorator", "courseReferenceNumber": "14436", "faculty": [], "meetingTime": {"beginTime": null, "building": "TBA", "buildingDescription": "To Be Announced", "campus": "C", "campusDescription": "Riverside", "category": "01", "class": "net.hedtech.banner.general.overall.MeetingTimeDecorator", "courseReferenceNumber": "14436", "creditHourSession": 1.0, "endDate": "06/08/2007", "endTime": null, "friday": false, "hoursWeek": 0.0, "meetingScheduleType": "RES", "meetingType": "RES", "meetingTypeDescription": "Research", "monday": false, "room": null, "saturday": false, "startDate": "04/02/2007", "sunday": false, "term": "200720", "thursday": false, "tuesday": false, "wednesday": false}, "term": "200720"}], "reservedSeatSummary": null, "sectionAttributes": null, "instructionalMethod": "I", "instructionalMethodDescription": "In-Person"}, {"id": 448159, "term": "200720", "termDesc": "Spring 2007", "courseReferenceNumber": "14437", "partOfTerm": "1", "courseNumber": "290", "subject": "GER", "subjectDescription": "German", "sequenceNumber": "34G", "campusDescription": "Riverside", "scheduleTypeDescription": "Research", "courseTitle": "DIRECTED STUDIES", "creditHours": null, "maximumEnrollment": 30, "enrollment": 0, "seatsAvailable": 30, "waitCapacity": 0, "waitCount": 0, "waitAvailable": 0, "crossList": null, "crossListCapacity": null, "crossListCount": null, "crossListAvailable": null, "creditHourHigh": 6, "creditHourLow": 1, "creditHourIndicator": "TO", "openSection": true, "linkIdentifier": null, "isSectionLinked": false, "subjectCourse": "GER290", "faculty": [{"bannerId": "338025", "category": null, "class": "net.hedtech.banner.student.faculty.FacultyResultDecorator", "courseReferenceNumber": "14437", "displayName": "Grimm, Reinhold", "emailAddress": null, "primaryIndicator": true, "term": "200720"}], "meetingsFaculty": [{"category": "01", "class": "net.hedtech.banner.student.schedule.SectionSessionDecorator", "courseReferenceNumber": "14437", "faculty": [], "meetingTime": {"beginTime": null, "building": "TBA", "buildingDescription": "To Be Announced", "campus": "C", "campusDescription": "Riverside", "category": "01", "class": "net.hedtech.banner.general.overall.MeetingTimeDecorator", "courseReferenceNumber": "14437", "creditHourSession": 1.0, "endDate": "06/08/2007", "endTime": null, "friday": false, "hoursWeek": 0.0, "meetingScheduleType": "RES", "meetingType": "RES", "meetingTypeDescription": "Research", "monday": false, "room": null, "saturday": false, "startDate": "04/02/2007", "sunday": false, "term": "200720", "thursday": false, "tuesday": false, "wednesday": false}, "term": "200720"}], "reservedSeatSummary": null, "sectionAttributes": null, "instructionalMethod": "I", "instructionalMethodDescription": "In-Person"}, {"id": 448160, "term": "200720", "termDesc": "Spring 2007", "courseReferenceNumber": "14438", "partOfTerm": "1", "courseNumber": "291", "subject": "GER", "subjectDescription": "German", "sequenceNumber": "001", "campusDescription": "Riverside", "scheduleTypeDescription": "Tutorial", "courseTitle": "INDIVIDUAL STUDY", "creditHours": null, "maximumEnrollment": 999, "enrollment": 0, "seatsAvailable": 999, "waitCapacity": 0, "waitCount": 0, "waitAvailable": 0, "crossList": null, "crossListCapacity": null, "crossListCount": null, "crossListAvailable": null, "creditHourHigh": 6, "creditHourLow": 1, "creditHourIndicator": "TO", "openSection": true, "linkIdentifier": null, "isSectionLinked": false, "subjectCourse": "GER291", "faculty": [{"bannerId": "314395", "category": null, "class": "net.hedtech.banner.student.faculty.FacultyResultDecorator", "courseReferenceNumber": "14438", "displayName": "The Staff, .", "emailAddress": null, "primaryIndicator": true, "term": "200720"}], "meetingsFaculty": [{"category": "01", "class": "net.hedtech.banner.student.schedule.SectionSessionDecorator", "courseReferenceNumber": "14438", "faculty": [], "meetingTime": {"beginTime": null, "building": "TBA", "buildingDescription": "To Be Announced", "campus": "C", "campusDescription": "Riverside", "category": "01", "class": "net.hedtech.banner.general.overall.MeetingTimeDecorator", "courseReferenceNumber": "14438", "creditHourSession": 1.0, "endDate": "06/08/2007", "endTime": null, "friday": false, "hoursWeek": 0.0, "meetingScheduleType": "TUT", "meetingType": "TUT", "meetingTypeDescription": "Tutorial", "monday": false, "room": null, "saturday": false, "startDate": "04/02/2007", "sunday": false, "term": "200720", "thursday": false, "tuesday": false, "wednesday": false}, "term": "200720"}], "reservedSeatSummary": null, "sectionAttributes": null, "instructionalMethod": "I", "instructionalMethodDescription": "In-Person"}, {"id": 448161, "term": "200720", "termDesc": "Spring 2007", "courseReferenceNumber": "14439", "partOfTerm": "1", "courseNumber": "291", "subject": "GER", "subjectDescription": "German", "sequenceNumber": "02D", "campusDescription": "Riverside", "scheduleTypeDescription": "Tutorial", "courseTitle": "INDIVIDUAL STUDY", "creditHours": null, "maximumEnrollment": 30, "enrollment": 0, "seatsAvailable": 30, "waitCapacity": 0, "waitCount": 0, "waitAvailable": 0, "crossList": null, "crossListCapacity": null, "crossListCount": null, "crossListAvailable": null, "creditHourHigh": 6, "creditHourLow": 1, "creditHourIndicator": "TO", "openSection": true, "linkIdentifier": null, "isSectionLinked": false, "subjectCourse": "GER291", "faculty": [{"bannerId": "351868", "category": null, "class": "net.hedtech.banner.student.faculty.FacultyResultDecorator", "courseReferenceNumber": "14439", "displayName": "Daviau, Donald", "emailAddress": null, "primaryIndicator": true, "term": "200720"}], "meetingsFaculty": [{"category": "01", "class": "net.hedtech.banner.student.schedule.SectionSessionDecorator", "courseReferenceNumber": "14439", "faculty": [], "meetingTime": {"beginTime": null, "building": "TBA", "buildingDescription": "To Be Announced", "campus": "C", "campusDescription": "Riverside", "category": "01", "class": "net.hedtech.banner.general.overall.MeetingTimeDecorator", "courseReferenceNumber": "14439", "creditHourSession": 1.0, "endDate": "06/08/2007", "endTime": null, "friday": false, "hoursWeek": 0.0, "meetingScheduleType": "TUT", "meetingType": "TUT", "meetingTypeDescription": "Tutorial", "monday": false, "room": null, "saturday": false, "startDate": "04/02/2007", "sunday": false, "term": "200720", "thursday": false, "tuesday": false, "wednesday": false}, "term": "200720"}], "reservedSeatSummary": null, "sectionAttributes": null, "instructionalMethod": "I", "instructionalMethodDescription": "In-Person"}, {"id": 448162, "term": "200720", "termDesc": "Spring 2007", "courseReferenceNumber": "14440", "partOfTerm": "1", "courseNumber": "291", "subject": "GER", "subjectDescription": "German", "sequenceNumber": "11G", "campusDescription": "Riverside", "scheduleTypeDescription": "Tutorial", "courseTitle": "INDIVIDUAL STUDY", "creditHours": null, "maximumEnrollment": 30, "enrollment": 0, "seatsAvailable": 30, "waitCapacity": 0, "waitCount": 0, "waitAvailable": 0, "crossList": null, "crossListCapacity": null, "crossListCount": null, "crossListAvailable": null, "creditHourHigh": 6, "creditHourLow": 1, "creditHourIndicator": "TO", "openSection": true, "linkIdentifier": null, "isSectionLinked": false, "subjectCourse": "GER291", "faculty": [{"bannerId": "335458", "category": null, "class": "net.hedtech.banner.student.faculty.FacultyResultDecorator", "courseReferenceNumber": "14440", "displayName": "Gugelberger, Georg", "emailAddress": "georg.gugelberger@ucr.edu", "primaryIndicator": true, "term": "200720"}], "meetingsFaculty": [{"category": "01", "class": "net.hedtech.banner.student.schedule.SectionSessionDecorator", "courseReferenceNumber": "14440", "faculty": [], "meetingTime": {"beginTime": null, "building": "TBA", "buildingDescription": "To Be Announced", "campus": "C", "campusDescription": "Riverside", "category": "01", "class": "net.hedtech.banner.general.overall.MeetingTimeDecorator", "courseReferenceNumber": "14440", "creditHourSession": 1.0, "endDate": "06/08/2007", "endTime": null, "friday": false, "hoursWeek": 0.0, "meetingScheduleType": "TUT", "meetingType": "TUT", "meetingTypeDescription": "Tutorial", "monday": false, "room": null, "saturday": false, "startDate": "04/02/2007", "sunday": false, "term": "200720", "thursday": false, "tuesday": false, "wednesday": false}, "term": "200720"}], "reservedSeatSummary": null, "sectionAttributes": null, "instructionalMethod": "I", "instructionalMethodDescription": "In-Person"}, {"id": 448163, "term": "200720", "termDesc": "Spring 2007", "courseReferenceNumber": "14441", "partOfTerm": "1", "courseNumber": "291", "subject": "GER", "subjectDescription": "German", "sequenceNumber": "25H", "campusDescription": "Riverside", "scheduleTypeDescription": "Tutorial", "courseTitle": "INDIVIDUAL STUDY", "creditHours": null, "maximumEnrollment": 30, "enrollment": 0, "seatsAvailable": 30, "waitCapacity": 0, "waitCount": 0, "waitAvailable": 0, "crossList": null, "crossListCapacity": null, "crossListCount": null, "crossListAvailable": null, "creditHourHigh": 6, "creditHourLow": 1, "creditHourIndicator": "TO", "openSection": true, "linkIdentifier": null, "isSectionLinked": false, "subjectCourse": "GER291", "faculty": [{"bannerId": "335455", "category": null, "class": "net.hedtech.banner.student.faculty.FacultyResultDecorator", "courseReferenceNumber": "14441", "displayName": "Hammer, Stephanie", "emailAddress": "stephanie.hammer@ucr.edu", "primaryIndicator": true, "term": "200720"}], "meetingsFaculty": [{"category": "01", "class": "net.hedtech.banner.student.schedule.SectionSessionDecorator", "courseReferenceNumber": "14441", "faculty": [], "meetingTime": {"beginTime": null, "building": "TBA", "buildingDescription": "To Be Announced", "campus": "C", "campusDescription": "Riverside", "category": "01", "class": "net.hedtech.banner.general.overall.MeetingTimeDecorator", "courseReferenceNumber": "14441", "creditHourSession": 1.0, "endDate": "06/08/2007", "endTime": null, "friday": false, "hoursWeek": 0.0, "meetingScheduleType": "TUT", "meetingType": "TUT", "meetingTypeDescription": "Tutorial", "monday": false, "room": null, "saturday": false, "startDate": "04/02/2007", "sunday": false, "term": "200720", "thursday": false, "tuesday": false, "wednesday": false}, "term": "200720"}], "reservedSeatSummary": null, "sectionAttributes": null, "instructionalMethod": "I", "instructionalMethodDescription": "In-Person"}, {"id": 448164, "term": "200720", "termDesc": "Spring 2007", "courseReferenceNumber": "14442", "partOfTerm": "1", "courseNumber": "291", "subject": "GER", "subjectDescription": "German", "sequenceNumber": "34G", "campusDescription": "Riverside", "scheduleTypeDescription": "Tutorial", "courseTitle": "INDIVIDUAL STUDY", "creditHours": null, "maximumEnrollment": 30, "enrollment": 0, "seatsAvailable": 30, "waitCapacity": 0, "waitCount": 0, "waitAvailable": 0, "crossList": null, "crossListCapacity": null, "crossListCount": null, "crossListAvailable": null, "creditHourHigh": 6, "creditHourLow": 1, "creditHourIndicator": "TO", "openSection": true, "linkIdentifier": null, "isSectionLinked": false, "subjectCourse": "GER291", "faculty": [{"bannerId": "338025", "category": null, "class": "net.hedtech.banner.student.faculty.FacultyResultDecorator", "courseReferenceNumber": "14442", "displayName": "Grimm, Reinhold", "emailAddress": null, "primaryIndicator": true, "term": "200720"}], "meetingsFaculty": [{"category": "01", "class": "net.hedtech.banner.student.schedule.SectionSessionDecorator", "courseReferenceNumber": "14442", "faculty": [], "meetingTime": {"beginTime": null, "building": "TBA", "buildingDescription": "To Be Announced", "campus": "C", "campusDescription": "Riverside", "category": "01", "class": "net.hedtech.banner.general.overall.MeetingTimeDecorator", "courseReferenceNumber": "14442", "creditHourSession": 1.0, "endDate": "06/08/2007", "endTime": null, "friday": false, "hoursWeek": 0.0, "meetingScheduleType": "TUT", "meetingType": "TUT", "meetingTypeDescription": "Tutorial", "monday": false, "room": null, "saturday": false, "startDate": "04/02/2007", "sunday": false, "term": "200720", "thursday": false, "tuesday": false, "wednesday": false}, "term": "200720"}], "reservedSeatSummary": null, "sectionAttributes": null, "instructionalMethod": "I", "instructionalMethodDescription": "In-Person"}, {"id": 448165, "term": "200720", "termDesc": "Spring 2007", "courseReferenceNumber": "14443", "partOfTerm": "1", "courseNumber": "291", "subject": "GER", "subjectDescription": "German", "sequenceNumber": "58S", "campusDescription": "Riverside", "scheduleTypeDescription": "Tutorial", "courseTitle": "INDIVIDUAL STUDY", "creditHours": null, "maximumEnrollment": 30, "enrollment": 0, "seatsAvailable": 30, "waitCapacity": 0, "waitCount": 0, "waitAvailable": 0, "crossList": null, "crossListCapacity": null, "crossListCount": null, "crossListAvailable": null, "creditHourHigh": 6, "creditHourLow": 1, "creditHourIndicator": "TO", "openSection": true, "linkIdentifier": null, "isSectionLinked": false, "subjectCourse": "GER291", "faculty": [{"bannerId": "336083", "category": null, "class": "net.hedtech.banner.student.faculty.FacultyResultDecorator", "courseReferenceNumber": "14443", "displayName": "Slusser, George", "emailAddress": "george.slusser@ucr.edu", "primaryIndicator": true, "term": "200720"}], "meetingsFaculty": [{"category": "01", "class": "net.hedtech.banner.student.schedule.SectionSessionDecorator", "courseReferenceNumber": "14443", "faculty": [], "meetingTime": {"beginTime": null, "building": "TBA", "buildingDescription": "To Be Announced", "campus": "C", "campusDescription": "Riverside", "category": "01", "class": "net.hedtech.banner.general.overall.MeetingTimeDecorator", "courseReferenceNumber": "14443", "creditHourSession": 1.0, "endDate": "06/08/2007", "endTime": null, "friday": false, "hoursWeek": 0.0, "meetingScheduleType": "TUT", "meetingType": "TUT", "meetingTypeDescription": "Tutorial", "monday": false, "room": null, "saturday": false, "startDate": "04/02/2007", "sunday": false, "term": "200720", "thursday": false, "tuesday": false, "wednesday": false}, "term": "200720"}], "reservedSeatSummary": null, "sectionAttributes": null, "instructionalMethod": "I", "instructionalMethodDescription": "In-Person"}, {"id": 448166, "term": "200720", "termDesc": "Spring 2007", "courseReferenceNumber": "14444", "partOfTerm": "1", "courseNumber": "292", "subject": "GER", "subjectDescription": "German", "sequenceNumber": "02D", "campusDescription": "Riverside", "scheduleTypeDescription": "Research", "courseTitle": "CONCRRNT ANALYTICAL STUDIES", "creditHours": 2, "maximumEnrollment": 30, "enrollment": 0, "seatsAvailable": 30, "waitCapacity": 0, "waitCount": 0, "waitAvailable": 0, "crossList": null, "crossListCapacity": null, "crossListCount": null, "crossListAvailable": null, "creditHourHigh": null, "creditHourLow": 2, "creditHourIndicator": null, "openSection": true, "linkIdentifier": null, "isSectionLinked": false, "subjectCourse": "GER292", "faculty": [{"bannerId": "351868", "category": null, "class": "net.hedtech.banner.student.faculty.FacultyResultDecorator", "courseReferenceNumber": "14444", "displayName": "Daviau, Donald", "emailAddress": null, "primaryIndicator": true, "term": "200720"}], "meetingsFaculty": [{"category": "01", "class": "net.hedtech.banner.student.schedule.SectionSessionDecorator", "courseReferenceNumber": "14444", "faculty": [], "meetingTime": {"beginTime": null, "building": "TBA", "buildingDescription": "To Be Announced", "campus": "C", "campusDescription": "Riverside", "category": "01", "class": "net.hedtech.banner.general.overall.MeetingTimeDecorator", "courseReferenceNumber": "14444", "creditHourSession": 2.0, "endDate": "06/08/2007", "endTime": null, "friday": false, "hoursWeek": 0.0, "meetingScheduleType": "RES", "meetingType": "RES", "meetingTypeDescription": "Research", "monday": false, "room": null, "saturday": false, "startDate": "04/02/2007", "sunday": false, "term": "200720", "thursday": false, "tuesday": false, "wednesday": false}, "term": "200720"}], "reservedSeatSummary": null, "sectionAttributes": null, "instructionalMethod": "I", "instructionalMethodDescription": "In-Person"}, {"id": 448167, "term": "200720", "termDesc": "Spring 2007", "courseReferenceNumber": "14445", "partOfTerm": "1", "courseNumber": "292", "subject": "GER", "subjectDescription": "German", "sequenceNumber": "11G", "campusDescription": "Riverside", "scheduleTypeDescription": "Research", "courseTitle": "CONCRRNT ANALYTICAL STUDIES", "creditHours": 2, "maximumEnrollment": 30, "enrollment": 0, "seatsAvailable": 30, "waitCapacity": 0, "waitCount": 0, "waitAvailable": 0, "crossList": null, "crossListCapacity": null, "crossListCount": null, "crossListAvailable": null, "creditHourHigh": null, "creditHourLow": 2, "creditHourIndicator": null, "openSection": true, "linkIdentifier": null, "isSectionLinked": false, "subjectCourse": "GER292", "faculty": [{"bannerId": "335458", "category": null, "class": "net.hedtech.banner.student.faculty.FacultyResultDecorator", "courseReferenceNumber": "14445", "displayName": "Gugelberger, Georg", "emailAddress": "georg.gugelberger@ucr.edu", "primaryIndicator": true, "term": "200720"}], "meetingsFaculty": [{"category": "01", "class": "net.hedtech.banner.student.schedule.SectionSessionDecorator", "courseReferenceNumber": "14445", "faculty": [], "meetingTime": {"beginTime": null, "building": "TBA", "buildingDescription": "To Be Announced", "campus": "C", "campusDescription": "Riverside", "category": "01", "class": "net.hedtech.banner.general.overall.MeetingTimeDecorator", "courseReferenceNumber": "14445", "creditHourSession": 2.0, "endDate": "06/08/2007", "endTime": null, "friday": false, "hoursWeek": 0.0, "meetingScheduleType": "RES", "meetingType": "RES", "meetingTypeDescription": "Research", "monday": false, "room": null, "saturday": false, "startDate": "04/02/2007", "sunday": false, "term": "200720", "thursday": false, "tuesday": false, "wednesday": false}, "term": "200720"}], "reservedSeatSummary": null, "sectionAttributes": null, "instructionalMethod": "I", "instructionalMethodDescription": "In-Person"}, {"id": 448168, "term": "200720", "termDesc": "Spring 2007", "courseReferenceNumber": "14446", "partOfTerm": "1", "courseNumber": "292", "subject": "GER", "subjectDescription": "German", "sequenceNumber": "25H", "campusDescription": "Riverside", "scheduleTypeDescription": "Research", "courseTitle": "CONCRRNT ANALYTICAL STUDIES", "creditHours": 2, "maximumEnrollment": 30, "enrollment": 0, "seatsAvailable": 30, "waitCapacity": 0, "waitCount": 0, "waitAvailable": 0, "crossList": null, "crossListCapacity": null, "crossListCount": null, "crossListAvailable": null, "creditHourHigh": null, "creditHourLow": 2, "creditHourIndicator": null, "openSection": true, "linkIdentifier": null, "isSectionLinked": false, "subjectCourse": "GER292", "faculty": [{"bannerId": "335455", "category": null, "class": "net.hedtech.banner.student.faculty.FacultyResultDecorator", "courseReferenceNumber": "14446", "displayName": "Hammer, Stephanie", "emailAddress": "stephanie.hammer@ucr.edu", "primaryIndicator": true, "term": "200720"}], "meetingsFaculty": [{"category": "01", "class": "net.hedtech.banner.student.schedule.SectionSessionDecorator", "courseReferenceNumber": "14446", "faculty": [], "meetingTime": {"beginTime": null, "building": "TBA", "buildingDescription": "To Be Announced", "campus": "C", "campusDescription": "Riverside", "category": "01", "class": "net.hedtech.banner.general.overall.MeetingTimeDecorator", "courseReferenceNumber": "14446", "creditHourSession": 2.0, "endDate": "06/08/2007", "endTime": null, "friday": false, "hoursWeek": 0.0, "meetingScheduleType": "RES", "meetingType": "RES", "meetingTypeDescription": "Research", "monday": false, "room": null, "saturday": false, "startDate": "04/02/2007", "sunday": false, "term": "200720", "thursday": false, "tuesday": false, "wednesday": false}, "term": "200720"}], "reservedSeatSummary": null, "sectionAttributes": null, "instructionalMethod": "I", "instructionalMethodDescription": "In-Person"}, {"id": 448169, "term": "200720", "termDesc": "Spring 2007", "courseReferenceNumber": "14447", "partOfTerm": "1", "courseNumber": "292", "subject": "GER", "subjectDescription": "German", "sequenceNumber": "34G", "campusDescription": "Riverside", "scheduleTypeDescription": "Research", "courseTitle": "CONCRRNT ANALYTICAL STUDIES", "creditHours": 2, "maximumEnrollment": 30, "enrollment": 0, "seatsAvailable": 30, "waitCapacity": 0, "waitCount": 0, "waitAvailable": 0, "crossList": null, "crossListCapacity": null, "crossListCount": null, "crossListAvailable": null, "creditHourHigh": null, "creditHourLow": 2, "creditHourIndicator": null, "openSection": true, "linkIdentifier": null, "isSectionLinked": false, "subjectCourse": "GER292", "faculty": [{"bannerId": "338025", "category": null, "class": "net.hedtech.banner.student.faculty.FacultyResultDecorator", "courseReferenceNumber": "14447", "displayName": "Grimm, Reinhold", "emailAddress": null, "primaryIndicator": true, "term": "200720"}], "meetingsFaculty": [{"category": "01", "class": "net.hedtech.banner.student.schedule.SectionSessionDecorator", "courseReferenceNumber": "14447", "faculty": [], "meetingTime": {"beginTime": null, "building": "TBA", "buildingDescription": "To Be Announced", "campus": "C", "campusDescription": "Riverside", "category": "01", "class": "net.hedtech.banner.general.overall.MeetingTimeDecorator", "courseReferenceNumber": "14447", "creditHourSession": 2.0, "endDate": "06/08/2007", "endTime": null, "friday": false, "hoursWeek": 0.0, "meetingScheduleType": "RES", "meetingType": "RES", "meetingTypeDescription": "Research", "monday": false, "room": null, "saturday": false, "startDate": "04/02/2007", "sunday": false, "term": "200720", "thursday": false, "tuesday": false, "wednesday": false}, "term": "200720"}], "reservedSeatSummary": null, "sectionAttributes": null, "instructionalMethod": "I", "instructionalMethodDescription": "In-Person"}, {"id": 448170, "term": "200720", "termDesc": "Spring 2007", "courseReferenceNumber": "14448", "partOfTerm": "1", "courseNumber": "299", "subject": "GER", "subjectDescription": "German", "sequenceNumber": "001", "campusDescription": "Riverside", "scheduleTypeDescription": "Thesis", "courseTitle": "THESIS OR DISSERTATION", "creditHours": null, "maximumEnrollment": 999, "enrollment": 0, "seatsAvailable": 999, "waitCapacity": 0, "waitCount": 0, "waitAvailable": 0, "crossList": null, "crossListCapacity": null, "crossListCount": null, "crossListAvailable": null, "creditHourHigh": 12, "creditHourLow": 1, "creditHourIndicator": "TO", "openSection": true, "linkIdentifier": null, "isSectionLinked": false, "subjectCourse": "GER299", "faculty": [{"bannerId": "314395", "category": null, "class": "net.hedtech.banner.student.faculty.FacultyResultDecorator", "courseReferenceNumber": "14448", "displayName": "The Staff, .", "emailAddress": null, "primaryIndicator": true, "term": "200720"}], "meetingsFaculty": [{"category": "01", "class": "net.hedtech.banner.student.schedule.SectionSessionDecorator", "courseReferenceNumber": "14448", "faculty": [], "meetingTime": {"beginTime": null, "building": "TBA", "buildingDescription": "To Be Announced", "campus": "C", "campusDescription": "Riverside", "category": "01", "class": "net.hedtech.banner.general.overall.MeetingTimeDecorator", "courseReferenceNumber": "14448", "creditHourSession": 1.0, "endDate": "06/08/2007", "endTime": null, "friday": false, "hoursWeek": 0.0, "meetingScheduleType": "THE", "meetingType": "THE", "meetingTypeDescription": "Thesis", "monday": false, "room": null, "saturday": false, "startDate": "04/02/2007", "sunday": false, "term": "200720", "thursday": false, "tuesday": false, "wednesday": false}, "term": "200720"}], "reservedSeatSummary": null, "sectionAttributes": null, "instructionalMethod": "I", "instructionalMethodDescription": "In-Person"}]}