{"code": "CLA", "description": "Classical Studies", "entries": 8, "data": [{"id": 582512, "term": "201210", "termDesc": "Winter 2012", "courseReferenceNumber": "28651", "partOfTerm": "1", "courseNumber": "010B", "subject": "CLA", "subjectDescription": "Classical Studies", "sequenceNumber": "001", "campusDescription": "Riverside", "scheduleTypeDescription": "Lecture", "courseTitle": "ANC CVLZTION:CLASSICAL GREECE", "creditHours": 4, "maximumEnrollment": 140, "enrollment": 148, "seatsAvailable": -8, "waitCapacity": 10, "waitCount": 0, "waitAvailable": 10, "crossList": null, "crossListCapacity": null, "crossListCount": null, "crossListAvailable": null, "creditHourHigh": null, "creditHourLow": 4, "creditHourIndicator": null, "openSection": true, "linkIdentifier": null, "isSectionLinked": false, "subjectCourse": "CLA010B", "faculty": [{"bannerId": "108433", "category": null, "class": "net.hedtech.banner.student.faculty.FacultyResultDecorator", "courseReferenceNumber": "28651", "displayName": "Chung, Angela", "emailAddress": "angela.chung002@email.ucr.edu", "primaryIndicator": false, "term": "201210"}, {"bannerId": "106197", "category": null, "class": "net.hedtech.banner.student.faculty.FacultyResultDecorator", "courseReferenceNumber": "28651", "displayName": "Bellum, Daniel", "emailAddress": "daniel.bellum@email.ucr.edu", "primaryIndicator": false, "term": "201210"}, {"bannerId": "96824", "category": null, "class": "net.hedtech.banner.student.faculty.FacultyResultDecorator", "courseReferenceNumber": "28651", "displayName": "Raschke, Wendy", "emailAddress": "wendy.raschke@ucr.edu", "primaryIndicator": true, "term": "201210"}], "meetingsFaculty": [{"category": "01", "class": "net.hedtech.banner.student.schedule.SectionSessionDecorator", "courseReferenceNumber": "28651", "faculty": [], "meetingTime": {"beginTime": "1310", "building": "HMNSS", "buildingDescription": "Humanities and Social Sciences", "campus": "C", "campusDescription": "Riverside", "category": "01", "class": "net.hedtech.banner.general.overall.MeetingTimeDecorator", "courseReferenceNumber": "28651", "creditHourSession": 4.0, "endDate": "03/16/2012", "endTime": "1400", "friday": true, "hoursWeek": 3.0, "meetingScheduleType": "LEC", "meetingType": "LEC", "meetingTypeDescription": "Lecture", "monday": true, "room": "1501", "saturday": false, "startDate": "01/09/2012", "sunday": false, "term": "201210", "thursday": false, "tuesday": false, "wednesday": true}, "term": "201210"}], "reservedSeatSummary": null, "sectionAttributes": null, "instructionalMethod": "I", "instructionalMethodDescription": "In-Person"}, {"id": 582513, "term": "201210", "termDesc": "Winter 2012", "courseReferenceNumber": "28652", "partOfTerm": "1", "courseNumber": "030", "subject": "CLA", "subjectDescription": "Classical Studies", "sequenceNumber": "001", "campusDescription": "Riverside", "scheduleTypeDescription": "Lecture", "courseTitle": "SCNCE WORD:GRK &amp; LAT ROOTS", "creditHours": 4, "maximumEnrollment": 100, "enrollment": 100, "seatsAvailable": 0, "waitCapacity": 2, "waitCount": 0, "waitAvailable": 2, "crossList": null, "crossListCapacity": null, "crossListCount": null, "crossListAvailable": null, "creditHourHigh": null, "creditHourLow": 4, "creditHourIndicator": null, "openSection": true, "linkIdentifier": null, "isSectionLinked": false, "subjectCourse": "CLA030", "faculty": [{"bannerId": "106808", "category": null, "class": "net.hedtech.banner.student.faculty.FacultyResultDecorator", "courseReferenceNumber": "28652", "displayName": "Syed Abu Bakar, Syed", "emailAddress": "syed.syedabubakar@email.ucr.edu", "primaryIndicator": false, "term": "201210"}, {"bannerId": "86129", "category": null, "class": "net.hedtech.banner.student.faculty.FacultyResultDecorator", "courseReferenceNumber": "28652", "displayName": "King, Benjamin", "emailAddress": "benjamin.king@ucr.edu", "primaryIndicator": true, "term": "201210"}], "meetingsFaculty": [{"category": "01", "class": "net.hedtech.banner.student.schedule.SectionSessionDecorator", "courseReferenceNumber": "28652", "faculty": [], "meetingTime": {"beginTime": "1410", "building": "HMNSS", "buildingDescription": "Humanities and Social Sciences", "campus": "C", "campusDescription": "Riverside", "category": "01", "class": "net.hedtech.banner.general.overall.MeetingTimeDecorator", "courseReferenceNumber": "28652", "creditHourSession": 4.0, "endDate": "03/16/2012", "endTime": "1500", "friday": true, "hoursWeek": 3.0, "meetingScheduleType": "LEC", "meetingType": "LEC", "meetingTypeDescription": "Lecture", "monday": true, "room": "1501", "saturday": false, "startDate": "01/09/2012", "sunday": false, "term": "201210", "thursday": false, "tuesday": false, "wednesday": true}, "term": "201210"}], "reservedSeatSummary": null, "sectionAttributes": null, "instructionalMethod": "I", "instructionalMethodDescription": "In-Person"}, {"id": 582514, "term": "201210", "termDesc": "Winter 2012", "courseReferenceNumber": "21510", "partOfTerm": "1", "courseNumber": "102", "subject": "CLA", "subjectDescription": "Classical Studies", "sequenceNumber": "001", "campusDescription": "Riverside", "scheduleTypeDescription": "Lecture", "courseTitle": "ANCNT CIVLIZATNS&amp;LATR IDENTIES", "creditHours": 4, "maximumEnrollment": 40, "enrollment": 13, "seatsAvailable": 27, "waitCapacity": 0, "waitCount": 0, "waitAvailable": 0, "crossList": "CF", "crossListCapacity": 40, "crossListCount": 29, "crossListAvailable": 11, "creditHourHigh": null, "creditHourLow": 4, "creditHourIndicator": null, "openSection": true, "linkIdentifier": null, "isSectionLinked": false, "subjectCourse": "CLA102", "faculty": [{"bannerId": "89608", "category": null, "class": "net.hedtech.banner.student.faculty.FacultyResultDecorator", "courseReferenceNumber": "21510", "displayName": "Maier, Hendrik", "emailAddress": "hendrik.maier@ucr.edu", "primaryIndicator": true, "term": "201210"}], "meetingsFaculty": [{"category": "01", "class": "net.hedtech.banner.student.schedule.SectionSessionDecorator", "courseReferenceNumber": "21510", "faculty": [], "meetingTime": {"beginTime": "1540", "building": "SPR", "buildingDescription": "Sproul Hall", "campus": "C", "campusDescription": "Riverside", "category": "01", "class": "net.hedtech.banner.general.overall.MeetingTimeDecorator", "courseReferenceNumber": "21510", "creditHourSession": 4.0, "endDate": "03/16/2012", "endTime": "1700", "friday": false, "hoursWeek": 3.0, "meetingScheduleType": "LEC", "meetingType": "LEC", "meetingTypeDescription": "Lecture", "monday": false, "room": "2339", "saturday": false, "startDate": "01/09/2012", "sunday": false, "term": "201210", "thursday": true, "tuesday": true, "wednesday": false}, "term": "201210"}, {"category": "02", "class": "net.hedtech.banner.student.schedule.SectionSessionDecorator", "courseReferenceNumber": "21510", "faculty": [], "meetingTime": {"beginTime": null, "building": "TBA", "buildingDescription": "To Be Announced", "campus": "C", "campusDescription": "Riverside", "category": "02", "class": "net.hedtech.banner.general.overall.MeetingTimeDecorator", "courseReferenceNumber": "21510", "creditHourSession": 0.0, "endDate": "03/16/2012", "endTime": null, "friday": false, "hoursWeek": 0.0, "meetingScheduleType": "RES", "meetingType": "RES", "meetingTypeDescription": "Research", "monday": false, "room": null, "saturday": false, "startDate": "01/09/2012", "sunday": false, "term": "201210", "thursday": false, "tuesday": false, "wednesday": false}, "term": "201210"}], "reservedSeatSummary": null, "sectionAttributes": null, "instructionalMethod": "I", "instructionalMethodDescription": "In-Person"}, {"id": 582515, "term": "201210", "termDesc": "Winter 2012", "courseReferenceNumber": "28653", "partOfTerm": "1", "courseNumber": "114", "subject": "CLA", "subjectDescription": "Classical Studies", "sequenceNumber": "001", "campusDescription": "Riverside", "scheduleTypeDescription": "Lecture", "courseTitle": "THE CLASSICAL TRADITION", "creditHours": 4, "maximumEnrollment": 40, "enrollment": 31, "seatsAvailable": 9, "waitCapacity": 1, "waitCount": 0, "waitAvailable": 1, "crossList": "CD", "crossListCapacity": 40, "crossListCount": 40, "crossListAvailable": 0, "creditHourHigh": null, "creditHourLow": 4, "creditHourIndicator": null, "openSection": true, "linkIdentifier": null, "isSectionLinked": false, "subjectCourse": "CLA114", "faculty": [{"bannerId": "86129", "category": null, "class": "net.hedtech.banner.student.faculty.FacultyResultDecorator", "courseReferenceNumber": "28653", "displayName": "King, Benjamin", "emailAddress": "benjamin.king@ucr.edu", "primaryIndicator": true, "term": "201210"}], "meetingsFaculty": [{"category": "01", "class": "net.hedtech.banner.student.schedule.SectionSessionDecorator", "courseReferenceNumber": "28653", "faculty": [], "meetingTime": {"beginTime": "1210", "building": "INTS", "buildingDescription": "CHASS Interdisciplinary-South", "campus": "C", "campusDescription": "Riverside", "category": "01", "class": "net.hedtech.banner.general.overall.MeetingTimeDecorator", "courseReferenceNumber": "28653", "creditHourSession": 4.0, "endDate": "03/16/2012", "endTime": "1300", "friday": true, "hoursWeek": 3.0, "meetingScheduleType": "LEC", "meetingType": "LEC", "meetingTypeDescription": "Lecture", "monday": true, "room": "1121", "saturday": false, "startDate": "01/09/2012", "sunday": false, "term": "201210", "thursday": false, "tuesday": false, "wednesday": true}, "term": "201210"}], "reservedSeatSummary": null, "sectionAttributes": null, "instructionalMethod": "I", "instructionalMethodDescription": "In-Person"}, {"id": 582516, "term": "201210", "termDesc": "Winter 2012", "courseReferenceNumber": "29325", "partOfTerm": "1", "courseNumber": "121", "subject": "CLA", "subjectDescription": "Classical Studies", "sequenceNumber": "001", "campusDescription": "Riverside", "scheduleTypeDescription": "Lecture", "courseTitle": "MONARCHY", "creditHours": 4, "maximumEnrollment": 80, "enrollment": 2, "seatsAvailable": 78, "waitCapacity": 10, "waitCount": 0, "waitAvailable": 10, "crossList": "GD", "crossListCapacity": 80, "crossListCount": 81, "crossListAvailable": 0, "creditHourHigh": null, "creditHourLow": 4, "creditHourIndicator": null, "openSection": true, "linkIdentifier": null, "isSectionLinked": false, "subjectCourse": "CLA121", "faculty": [{"bannerId": "88533", "category": null, "class": "net.hedtech.banner.student.faculty.FacultyResultDecorator", "courseReferenceNumber": "29325", "displayName": "Laursen, John", "emailAddress": "john.laursen@ucr.edu", "primaryIndicator": true, "term": "201210"}], "meetingsFaculty": [{"category": "01", "class": "net.hedtech.banner.student.schedule.SectionSessionDecorator", "courseReferenceNumber": "29325", "faculty": [], "meetingTime": {"beginTime": "0910", "building": "SPR", "buildingDescription": "Sproul Hall", "campus": "C", "campusDescription": "Riverside", "category": "01", "class": "net.hedtech.banner.general.overall.MeetingTimeDecorator", "courseReferenceNumber": "29325", "creditHourSession": 4.0, "endDate": "03/16/2012", "endTime": "1000", "friday": true, "hoursWeek": 3.0, "meetingScheduleType": "LEC", "meetingType": "LEC", "meetingTypeDescription": "Lecture", "monday": true, "room": "1340", "saturday": false, "startDate": "01/09/2012", "sunday": false, "term": "201210", "thursday": false, "tuesday": false, "wednesday": true}, "term": "201210"}, {"category": "02", "class": "net.hedtech.banner.student.schedule.SectionSessionDecorator", "courseReferenceNumber": "29325", "faculty": [], "meetingTime": {"beginTime": null, "building": "TBA", "buildingDescription": "To Be Announced", "campus": "C", "campusDescription": "Riverside", "category": "02", "class": "net.hedtech.banner.general.overall.MeetingTimeDecorator", "courseReferenceNumber": "29325", "creditHourSession": 0.0, "endDate": "03/16/2012", "endTime": null, "friday": false, "hoursWeek": 0.0, "meetingScheduleType": "RES", "meetingType": "RES", "meetingTypeDescription": "Research", "monday": false, "room": null, "saturday": false, "startDate": "01/09/2012", "sunday": false, "term": "201210", "thursday": false, "tuesday": false, "wednesday": false}, "term": "201210"}], "reservedSeatSummary": null, "sectionAttributes": null, "instructionalMethod": "I", "instructionalMethodDescription": "In-Person"}, {"id": 582517, "term": "201210", "termDesc": "Winter 2012", "courseReferenceNumber": "21511", "partOfTerm": "1", "courseNumber": "190", "subject": "CLA", "subjectDescription": "Classical Studies", "sequenceNumber": "001", "campusDescription": "Riverside", "scheduleTypeDescription": "Tutorial", "courseTitle": "SPECIAL STUDIES", "creditHours": null, "maximumEnrollment": 30, "enrollment": 0, "seatsAvailable": 30, "waitCapacity": 0, "waitCount": 0, "waitAvailable": 0, "crossList": null, "crossListCapacity": null, "crossListCount": null, "crossListAvailable": null, "creditHourHigh": 5, "creditHourLow": 1, "creditHourIndicator": "TO", "openSection": true, "linkIdentifier": null, "isSectionLinked": false, "subjectCourse": "CLA190", "faculty": [{"bannerId": "78729", "category": null, "class": "net.hedtech.banner.student.faculty.FacultyResultDecorator", "courseReferenceNumber": "21511", "displayName": "The Staff, .", "emailAddress": null, "primaryIndicator": true, "term": "201210"}], "meetingsFaculty": [{"category": "01", "class": "net.hedtech.banner.student.schedule.SectionSessionDecorator", "courseReferenceNumber": "21511", "faculty": [], "meetingTime": {"beginTime": null, "building": "TBA", "buildingDescription": "To Be Announced", "campus": "C", "campusDescription": "Riverside", "category": "01", "class": "net.hedtech.banner.general.overall.MeetingTimeDecorator", "courseReferenceNumber": "21511", "creditHourSession": 1.0, "endDate": "03/16/2012", "endTime": null, "friday": false, "hoursWeek": 0.0, "meetingScheduleType": "TUT", "meetingType": "TUT", "meetingTypeDescription": "Tutorial", "monday": false, "room": null, "saturday": false, "startDate": "01/09/2012", "sunday": false, "term": "201210", "thursday": false, "tuesday": false, "wednesday": false}, "term": "201210"}], "reservedSeatSummary": null, "sectionAttributes": null, "instructionalMethod": "I", "instructionalMethodDescription": "In-Person"}, {"id": 582518, "term": "201210", "termDesc": "Winter 2012", "courseReferenceNumber": "29676", "partOfTerm": "1", "courseNumber": "190", "subject": "CLA", "subjectDescription": "Classical Studies", "sequenceNumber": "35S", "campusDescription": "Riverside", "scheduleTypeDescription": "Tutorial", "courseTitle": "SPECIAL STUDIES", "creditHours": null, "maximumEnrollment": 30, "enrollment": 1, "seatsAvailable": 29, "waitCapacity": 0, "waitCount": 0, "waitAvailable": 0, "crossList": null, "crossListCapacity": null, "crossListCount": null, "crossListAvailable": null, "creditHourHigh": 5, "creditHourLow": 1, "creditHourIndicator": "TO", "openSection": true, "linkIdentifier": null, "isSectionLinked": false, "subjectCourse": "CLA190", "faculty": [{"bannerId": "97626", "category": null, "class": "net.hedtech.banner.student.faculty.FacultyResultDecorator", "courseReferenceNumber": "29676", "displayName": "Scanlon, Thomas", "emailAddress": "thomas.scanlon@ucr.edu", "primaryIndicator": true, "term": "201210"}], "meetingsFaculty": [{"category": "01", "class": "net.hedtech.banner.student.schedule.SectionSessionDecorator", "courseReferenceNumber": "29676", "faculty": [], "meetingTime": {"beginTime": null, "building": "TBA", "buildingDescription": "To Be Announced", "campus": "C", "campusDescription": "Riverside", "category": "01", "class": "net.hedtech.banner.general.overall.MeetingTimeDecorator", "courseReferenceNumber": "29676", "creditHourSession": 1.0, "endDate": "03/16/2012", "endTime": null, "friday": false, "hoursWeek": 0.0, "meetingScheduleType": "TUT", "meetingType": "TUT", "meetingTypeDescription": "Tutorial", "monday": false, "room": null, "saturday": false, "startDate": "01/09/2012", "sunday": false, "term": "201210", "thursday": false, "tuesday": false, "wednesday": false}, "term": "201210"}], "reservedSeatSummary": null, "sectionAttributes": null, "instructionalMethod": "I", "instructionalMethodDescription": "In-Person"}, {"id": 582519, "term": "201210", "termDesc": "Winter 2012", "courseReferenceNumber": "21513", "partOfTerm": "1", "courseNumber": "297", "subject": "CLA", "subjectDescription": "Classical Studies", "sequenceNumber": "001", "campusDescription": "Riverside", "scheduleTypeDescription": "Research", "courseTitle": "DIRECTED RESEARCH", "creditHours": null, "maximumEnrollment": 30, "enrollment": 0, "seatsAvailable": 30, "waitCapacity": 999, "waitCount": 0, "waitAvailable": 999, "crossList": null, "crossListCapacity": null, "crossListCount": null, "crossListAvailable": null, "creditHourHigh": 6, "creditHourLow": 1, "creditHourIndicator": "TO", "openSection": true, "linkIdentifier": null, "isSectionLinked": false, "subjectCourse": "CLA297", "faculty": [{"bannerId": "97626", "category": null, "class": "net.hedtech.banner.student.faculty.FacultyResultDecorator", "courseReferenceNumber": "21513", "displayName": "Scanlon, Thomas", "emailAddress": "thomas.scanlon@ucr.edu", "primaryIndicator": true, "term": "201210"}], "meetingsFaculty": [{"category": "01", "class": "net.hedtech.banner.student.schedule.SectionSessionDecorator", "courseReferenceNumber": "21513", "faculty": [], "meetingTime": {"beginTime": null, "building": "TBA", "buildingDescription": "To Be Announced", "campus": "C", "campusDescription": "Riverside", "category": "01", "class": "net.hedtech.banner.general.overall.MeetingTimeDecorator", "courseReferenceNumber": "21513", "creditHourSession": 1.0, "endDate": "03/16/2012", "endTime": null, "friday": false, "hoursWeek": 0.0, "meetingScheduleType": "RES", "meetingType": "RES", "meetingTypeDescription": "Research", "monday": false, "room": null, "saturday": false, "startDate": "01/09/2012", "sunday": false, "term": "201210", "thursday": false, "tuesday": false, "wednesday": false}, "term": "201210"}], "reservedSeatSummary": null, "sectionAttributes": null, "instructionalMethod": "I", "instructionalMethodDescription": "In-Person"}]}